report_not_covered_lines/__init__.py
report_not_covered_lines/__main__.py
report_not_covered_lines/report_not_covered_lines.py
review_style_gerrit/__init__.py
review_style_gerrit/__main__.py
review_style_gerrit/review_style_gerrit.py
review_style_gerrit-0.0.4.dist-info/LICENSE
review_style_gerrit-0.0.4.dist-info/METADATA
review_style_gerrit-0.0.4.dist-info/WHEEL
review_style_gerrit-0.0.4.dist-info/entry_points.txt
review_style_gerrit-0.0.4.dist-info/top_level.txt
review_style_gerrit-0.0.4.dist-info/RECORD
